pandadoc_cli/__init__.py
pandadoc_cli/cli.py
pandadoc_cli/config.py
pandadoc_cli/output.py
pandadoc_cli/prompts.py
pandadoc_cli/api/__init__.py
pandadoc_cli/api/copper.py
pandadoc_cli/api/pandadoc.py
pandadoc_cli/commands/__init__.py
pandadoc_cli/commands/config.py
pandadoc_cli/commands/contact.py
pandadoc_cli/commands/copper.py
pandadoc_cli/commands/doc.py
dc_pandadoc_cli-0.2.0.dist-info/METADATA
dc_pandadoc_cli-0.2.0.dist-info/WHEEL
dc_pandadoc_cli-0.2.0.dist-info/entry_points.txt
dc_pandadoc_cli-0.2.0.dist-info/RECORD
